<?xml version="1.0" encoding="utf-8"?>
<FrameLayout xmlns:android="http://schemas.android.com/apk/res/android" android:layout_width="-1" android:layout_height="-2">
	<LinearLayout android:gravity="0x10" android:orientation="0" android:layout_width="-1" android:layout_height="-1" android:minHeight="50dp">
		<ImageView android:layout_width="173670unknown unit:0x21" android:layout_height="304742unknown unit:0x21" android:src="r/f/eu.xml" android:layout_marginStart="23dp" />
		<LinearLayout android:orientation="1" android:layout_width="-2" android:layout_height="-2" android:layout_marginStart="275251unknown unit:0x21">
			<TextView android:textSize="14sp" android:textColor="r/n/g1.xml" android:id="false" android:layout_width="-2" android:layout_height="-2" />
			<TextView android:textSize="12sp" android:textColor="666666" android:id="false" android:layout_width="-2" android:layout_height="-2" />
		</LinearLayout>
	</LinearLayout>
	<View android:layout_gravity="0x30" android:id="false" android:background="c1c2c2" android:layout_width="-1" android:layout_height="2516583unknown unit:0x31" />
</FrameLayout>
